<annotation>
	<folder>n03745146</folder>
	<filename>n03745146_42658</filename>
	<source>
		<database>ImageNet database</database>
	</source>
	<size>
		<width>500</width>
		<height>375</height>
		<depth>3</depth>
	</size>
	<segmented>0</segmented>
	<object>
		<name>n13104059</name>
		<pose>Unspecified</pose>
		<truncated>0</truncated>
		<difficult>0</difficult>
		<bndbox>
			<xmin>29</xmin>
			<ymin>0</ymin>
			<xmax>161</xmax>
			<ymax>374</ymax>
		</bndbox>
	</object>
	<object>
		<name>n13104059</name>
		<pose>Unspecified</pose>
		<truncated>0</truncated>
		<difficult>0</difficult>
		<bndbox>
			<xmin>27</xmin>
			<ymin>0</ymin>
			<xmax>163</xmax>
			<ymax>374</ymax>
		</bndbox>
	</object>
	<object>
		<name>n03327234</name>
		<pose>Unspecified</pose>
		<truncated>0</truncated>
		<difficult>0</difficult>
		<bndbox>
			<xmin>2</xmin>
			<ymin>0</ymin>
			<xmax>425</xmax>
			<ymax>124</ymax>
		</bndbox>
	</object>
	<object>
		<name>n09416076</name>
		<pose>Unspecified</pose>
		<truncated>0</truncated>
		<difficult>0</difficult>
		<bndbox>
			<xmin>409</xmin>
			<ymin>185</ymin>
			<xmax>428</xmax>
			<ymax>202</ymax>
		</bndbox>
	</object>
	<object>
		<name>n00015388</name>
		<pose>Unspecified</pose>
		<truncated>0</truncated>
		<difficult>0</difficult>
		<bndbox>
			<xmin>185</xmin>
			<ymin>154</ymin>
			<xmax>364</xmax>
			<ymax>275</ymax>
		</bndbox>
	</object>
</annotation>